<annotation><filename>hall89.jpg</filename><folder>corridor</folder><source><sourceImage>Indoor collection organized by Aude Oliva</sourceImage><sourceAnnotation>LabelMe Webtool</sourceAnnotation></source><object><name>painting</name><deleted>0</deleted><verified>0</verified><date>28-Dec-2005 21:22:37</date><polygon><username>anonymous</username><pt><x>198</x><y>68</y></pt><pt><x>191</x><y>71</y></pt><pt><x>192</x><y>118</y></pt><pt><x>201</x><y>117</y></pt></polygon></object><object><name>lamp</name><deleted>0</deleted><verified>0</verified><date>11-Jan-2006 15:06:18</date><polygon><username>anonymous</username><pt><x>123</x><y>54</y></pt><pt><x>131</x><y>54</y></pt><pt><x>131</x><y>50</y></pt><pt><x>122</x><y>49</y></pt></polygon></object><object><name>lamp</name><deleted>0</deleted><verified>0</verified><date>11-Jan-2006 15:06:18</date><polygon><username>anonymous</username><pt><x>123</x><y>22</y></pt><pt><x>132</x><y>22</y></pt><pt><x>132</x><y>19</y></pt><pt><x>123</x><y>19</y></pt></polygon></object></annotation>